evaluatorspk/__init__.py
evaluatorspk/evaluator.py
evaluatorspk/test_evaluator.py
evaluatorspk-0.0.1.dist-info/licenses/LICENSE
evaluatorspk-0.0.1.dist-info/METADATA
evaluatorspk-0.0.1.dist-info/WHEEL
evaluatorspk-0.0.1.dist-info/top_level.txt
evaluatorspk-0.0.1.dist-info/RECORD
