Metadata-Version: 2.4
Name: evaluatorspk
Version: 0.0.1
Summary: A library for evaluating Retrieval-Augmented Generation (RAG) systems
Home-page: https://github.com/funnyPhani/evaluators
Author: Phani Siginamsetty
Author-email: siginamsettyphani@gmail.com
Classifier: Programming Language :: Python :: 3
Classifier: License :: OSI Approved :: MIT License
Classifier: Operating System :: OS Independent
Requires-Python: >=3.10
License-File: LICENSE
Requires-Dist: torch
Requires-Dist: sacrebleu
Requires-Dist: rouge-score
Requires-Dist: bert-score
Requires-Dist: transformers
Requires-Dist: nltk
Requires-Dist: textblob
Dynamic: author
Dynamic: author-email
Dynamic: classifier
Dynamic: description
Dynamic: description-content-type
Dynamic: home-page
Dynamic: license-file
Dynamic: requires-dist
Dynamic: requires-python
Dynamic: summary
